.coveragerc
.editorconfig
.gitignore
AUTHORS.rst
CONTRIBUTING.rst
HISTORY.rst
LICENSE
MANIFEST.in
README.rst
manage.py
requirements.txt
requirements_dev.txt
requirements_test.txt
runtests.py
setup.cfg
setup.py
tasks.py
tox.ini
.github/ISSUE_TEMPLATE.md
.github/workflows/main.yml
dj_2fa_social_auth.egg-info/PKG-INFO
dj_2fa_social_auth.egg-info/SOURCES.txt
dj_2fa_social_auth.egg-info/dependency_links.txt
dj_2fa_social_auth.egg-info/not-zip-safe
dj_2fa_social_auth.egg-info/requires.txt
dj_2fa_social_auth.egg-info/top_level.txt
docs/Makefile
docs/authors.rst
docs/conf.py
docs/contributing.rst
docs/history.rst
docs/index.rst
docs/installation.rst
docs/make.bat
docs/readme.rst
docs/usage.rst
social_2fa/__init__.py
social_2fa/apps.py
social_2fa/social_pipeline.py
social_2fa/urls.py
social_2fa/views.py
social_2fa/tests/.test_views.py.swp
social_2fa/tests/__init__.py
social_2fa/tests/test_pipeline.py
social_2fa/tests/test_views.py
tests/README.md
tests/__init__.py
tests/requirements.txt
tests/settings.py
tests/urls.py
tests/wsgi.py
tests/example/__init__.py
tests/example/urls.py