Metadata-Version: 2.1
Name: dj-2fa-social-auth
Version: 0.1.0
Summary: App connecting django-two-factor-auth and django-social-auth. If user authenticates through social auth, he will be enforced to go through 2FA (if he has it enabled).
Home-page: https://github.com/PetrDlouhy/dj-2fa-social-auth
Author: Petr Dlouhý
Author-email: petr.dlouhy@email.cz
License: BSD
Keywords: dj-2fa-social-auth
Platform: UNKNOWN
Classifier: Development Status :: 3 - Alpha
Classifier: Framework :: Django :: 1.11
Classifier: Framework :: Django :: 2.1
Classifier: Intended Audience :: Developers
Classifier: License :: OSI Approved :: BSD License
Classifier: Natural Language :: English
Classifier: Programming Language :: Python :: 2
Classifier: Programming Language :: Python :: 2.7
Classifier: Programming Language :: Python :: 3
Classifier: Programming Language :: Python :: 3.5
Classifier: Programming Language :: Python :: 3.6
License-File: LICENSE
License-File: AUTHORS.rst
